{"nodes": [{"id": "identity_users_table", "label": "identity_users", "file_type": "code", "source_file": "apps/api/src/db/schema/identity-users.ts", "source_location": null, "source_url": null, "captured_at": null, "author": null, "contributor": null}, {"id": "identity_users_email_split_concept", "label": "Spec-06 email-column removal (multi-row emails)", "file_type": "code", "source_file": "apps/api/src/db/schema/identity-users.ts", "source_location": null, "source_url": null, "captured_at": null, "author": null, "contributor": null}], "edges": [{"source": "identity_users_table", "target": "identity_users_email_split_concept", "relation": "rationale_for", "confidence": "EXTRACTED", "confidence_score": 1.0, "source_file": "apps/api/src/db/schema/identity-users.ts", "source_location": null, "weight": 1.0}], "hyperedges": []}